{
  "_class": "group",
  "booleanOperation": -1,
  "clippingMaskMode": 0,
  "do_objectID": "DADAEDFF-83A1-4CC9-B9F1-5DA5A5ABF843",
  "exportOptions": {
    "_class": "exportOptions",
    "do_objectID": "EFDC53BF-533D-485A-9297-D296BC2B9A38",
    "exportFormats": [
    ],
    "includedLayerIds": [
    ],
    "layerOptions": 0,
    "shouldTrim": false
  },
  "frame": {
    "_class": "rect",
    "constrainProportions": false,
    "do_objectID": "30378D94-2F84-406E-8002-0BD2E4A72D36",
    "height": 49,
    "width": 49,
    "x": 307,
    "y": 324
  },
  "groupLayout": {
    "_class": "MSImmutableFreeformGroupLayout",
    "do_objectID": "F31FF8AB-CAD0-41DF-9E1E-0432C402C58D"
  },
  "hasClickThrough": false,
  "hasClippingMask": false,
  "isFixedToViewport": false,
  "isFlippedHorizontal": false,
  "isFlippedVertical": false,
  "isLocked": false,
  "isVisible": true,
  "layerListExpandedType": 2,
  "layers": [
    {
      "class": "oval",
      "id": "BF68A4C8-AF45-44B1-ACA9-CFF02C2FA09C"
    },
    {
      "class": "symbolInstance",
      "id": "35157BC0-814C-413B-91DC-4DCB18BB0E9B"
    }
  ],
  "name": "Group 5",
  "nameIsFixed": false,
  "resizingConstraint": 63,
  "resizingType": 0,
  "rotation": 0,
  "shouldBreakMaskChain": false,
  "style": {
    "_class": "style",
    "do_objectID": "0C89F277-294D-4063-ACD2-6BEB07151733",
    "endMarkerType": 0,
    "miterLimit": 10,
    "startMarkerType": 0,
    "windingRule": 1
  }
}