{
  "_class": "shapePath",
  "booleanOperation": 0,
  "clippingMaskMode": 0,
  "do_objectID": "D900BD86-5A0C-4EDB-8DCF-B72452B94B09",
  "edited": true,
  "exportOptions": {
    "_class": "exportOptions",
    "do_objectID": "4D718FE8-E089-4C8C-8486-879D11D95488",
    "exportFormats": [
    ],
    "includedLayerIds": [
    ],
    "layerOptions": 0,
    "shouldTrim": false
  },
  "frame": {
    "_class": "rect",
    "constrainProportions": false,
    "do_objectID": "69C1865A-A3AC-4D9C-93D0-49C218C32C75",
    "height": 14.61844844164082,
    "width": 9.482061314822616,
    "x": 73.29075628045243,
    "y": 5.572764475804981
  },
  "hasClippingMask": false,
  "isClosed": true,
  "isFixedToViewport": false,
  "isFlippedHorizontal": false,
  "isFlippedVertical": false,
  "isLocked": false,
  "isVisible": true,
  "layerListExpandedType": 0,
  "name": "r",
  "nameIsFixed": true,
  "pointRadiusBehaviour": 1,
  "points": [
    {
      "_class": "curvePoint",
      "cornerRadius": 0,
      "curveFrom": "{1, 0.046122584651639147}",
      "curveMode": 4,
      "curveTo": "{1, 0.053753603974425586}",
      "hasCurveFrom": true,
      "hasCurveTo": false,
      "point": "{1, 0.053753603974425586}"
    },
    {
      "_class": "curvePoint",
      "cornerRadius": 0,
      "curveFrom": "{0.94117647058823528, 0.0384915653288527}",
      "curveMode": 4,
      "curveTo": "{1, 0.046122584651639147}",
      "hasCurveFrom": true,
      "hasCurveTo": true,
      "point": "{0.98823529411764777, 0.046122584651639147}"
    },
    {
      "_class": "curvePoint",
      "cornerRadius": 0,
      "curveFrom": "{0.29411764705882354, -0.0072945506078681346}",
      "curveMode": 4,
      "curveTo": "{0.78823529411764903, 0.015598507360491199}",
      "hasCurveFrom": true,
      "hasCurveTo": true,
      "point": "{0.70588235294117652, 0.00033646871491830943}"
    },
    {
      "_class": "curvePoint",
      "cornerRadius": 0,
      "curveFrom": "{0, 0.37425641553147576}",
      "curveMode": 4,
      "curveTo": "{0, 0.11480175855672148}",
      "hasCurveFrom": false,
      "hasCurveTo": true,
      "point": "{0, 0.37425641553147576}"
    },
    {
      "_class": "curvePoint",
      "cornerRadius": 0,
      "curveFrom": "{0, 1}",
      "curveMode": 4,
      "curveTo": "{0, 0.99236898067721357}",
      "hasCurveFrom": true,
      "hasCurveTo": false,
      "point": "{0, 0.99236898067721357}"
    },
    {
      "_class": "curvePoint",
      "cornerRadius": 0,
      "curveFrom": "{0.011764705882352273, 1}",
      "curveMode": 4,
      "curveTo": "{0.011764705882352273, 1}",
      "hasCurveFrom": false,
      "hasCurveTo": true,
      "point": "{0.011764705882352273, 1}"
    },
    {
      "_class": "curvePoint",
      "cornerRadius": 0,
      "curveFrom": "{0.31764705882352806, 1}",
      "curveMode": 4,
      "curveTo": "{0.30588235294117583, 1}",
      "hasCurveFrom": true,
      "hasCurveTo": false,
      "point": "{0.30588235294117583, 1}"
    },
    {
      "_class": "curvePoint",
      "cornerRadius": 0,
      "curveFrom": "{0.31764705882352806, 0.99236898067721357}",
      "curveMode": 4,
      "curveTo": "{0.31764705882352806, 0.99236898067721357}",
      "hasCurveFrom": false,
      "hasCurveTo": true,
      "point": "{0.31764705882352806, 0.99236898067721357}"
    },
    {
      "_class": "curvePoint",
      "cornerRadius": 0,
      "curveFrom": "{0.31764705882352806, 0.22926704839852574}",
      "curveMode": 4,
      "curveTo": "{0.31764705882352806, 0.37425641553147687}",
      "hasCurveFrom": true,
      "hasCurveTo": false,
      "point": "{0.31764705882352806, 0.37425641553147687}"
    },
    {
      "_class": "curvePoint",
      "cornerRadius": 0,
      "curveFrom": "{0.76470588235293779, 0.18348093246180491}",
      "curveMode": 3,
      "curveTo": "{0.4352941176470575, 0.18348093246180491}",
      "hasCurveFrom": true,
      "hasCurveTo": true,
      "point": "{0.69411764705882084, 0.18348093246180491}"
    },
    {
      "_class": "curvePoint",
      "cornerRadius": 0,
      "curveFrom": "{0.90588235294117181, 0.20637399043016533}",
      "curveMode": 4,
      "curveTo": "{0.85882352941176265, 0.19111195178459134}",
      "hasCurveFrom": true,
      "hasCurveTo": true,
      "point": "{0.89411764705881946, 0.20637399043016533}"
    },
    {
      "_class": "curvePoint",
      "cornerRadius": 0,
      "curveFrom": "{0.90588235294117181, 0.19874297110737887}",
      "curveMode": 4,
      "curveTo": "{0.90588235294117181, 0.20637399043016533}",
      "hasCurveFrom": false,
      "hasCurveTo": true,
      "point": "{0.90588235294117181, 0.19874297110737887}"
    }
  ],
  "resizingConstraint": 63,
  "resizingType": 0,
  "rotation": 0,
  "shouldBreakMaskChain": false,
  "style": {
    "_class": "style",
    "do_objectID": "7F58B8E4-7909-4297-8CE0-FCEE74AEA54E",
    "endMarkerType": 0,
    "fills": [
      {
        "_class": "fill",
        "color": {
          "_class": "color",
          "alpha": 1,
          "blue": 1,
          "green": 1,
          "red": 1
        },
        "fillType": 0,
        "isEnabled": true,
        "noiseIndex": 0,
        "noiseIntensity": 0,
        "patternFillType": 1,
        "patternTileScale": 1
      }
    ],
    "miterLimit": 10,
    "startMarkerType": 0,
    "windingRule": 0
  }
}