{
  "_class": "group",
  "booleanOperation": -1,
  "clippingMaskMode": 0,
  "do_objectID": "2C362474-BCD6-444B-801D-CB85C8907383",
  "exportOptions": {
    "_class": "exportOptions",
    "do_objectID": "84E02F71-9BC6-407B-B19B-42D2E5CD4686",
    "exportFormats": [
    ],
    "includedLayerIds": [
    ],
    "layerOptions": 0,
    "shouldTrim": false
  },
  "frame": {
    "_class": "rect",
    "constrainProportions": false,
    "do_objectID": "CA03BC1A-C0B1-43F3-91BA-EB6B7D77D5EA",
    "height": 49,
    "width": 49,
    "x": 307,
    "y": 267
  },
  "groupLayout": {
    "_class": "MSImmutableFreeformGroupLayout",
    "do_objectID": "22F661C9-34D6-402D-BF84-AABA515AC37B"
  },
  "hasClickThrough": false,
  "hasClippingMask": false,
  "isFixedToViewport": false,
  "isFlippedHorizontal": false,
  "isFlippedVertical": false,
  "isLocked": false,
  "isVisible": true,
  "layerListExpandedType": 0,
  "layers": [
    {
      "class": "oval",
      "id": "17C2C799-A126-4450-B049-45E97387031F"
    },
    {
      "class": "symbolInstance",
      "id": "4DB3DCE2-249D-4657-B5AF-43449BA4B08A"
    }
  ],
  "name": "Group 5",
  "nameIsFixed": false,
  "resizingConstraint": 63,
  "resizingType": 0,
  "rotation": 0,
  "shouldBreakMaskChain": false,
  "style": {
    "_class": "style",
    "do_objectID": "A7A90913-96E7-48BC-A4A6-A28376954973",
    "endMarkerType": 0,
    "miterLimit": 10,
    "startMarkerType": 0,
    "windingRule": 1
  }
}