{
  "_class": "group",
  "booleanOperation": -1,
  "clippingMaskMode": 0,
  "do_objectID": "D0915A14-BC94-4712-882C-F0F2EFDA76FB",
  "exportOptions": {
    "_class": "exportOptions",
    "do_objectID": "23E527AA-9F4D-4567-89F1-B0A72F35A4BA",
    "exportFormats": [
    ],
    "includedLayerIds": [
    ],
    "layerOptions": 0,
    "shouldTrim": false
  },
  "frame": {
    "_class": "rect",
    "constrainProportions": false,
    "do_objectID": "4F9FB4F3-1539-47D5-B2F5-046310A1B439",
    "height": 16,
    "width": 16,
    "x": 198,
    "y": 15
  },
  "groupLayout": {
    "_class": "MSImmutableFreeformGroupLayout",
    "do_objectID": "8C083226-53ED-477C-84AD-A97AE0158D0F"
  },
  "hasClickThrough": false,
  "hasClippingMask": false,
  "isFixedToViewport": false,
  "isFlippedHorizontal": false,
  "isFlippedVertical": false,
  "isLocked": false,
  "isVisible": true,
  "layerListExpandedType": 2,
  "layers": [
    {
      "class": "group",
      "id": "6DE23739-FAEE-4719-8650-B33C8BFA3135"
    }
  ],
  "name": "Group 4",
  "nameIsFixed": false,
  "resizingConstraint": 63,
  "resizingType": 0,
  "rotation": 0,
  "shouldBreakMaskChain": false,
  "style": {
    "_class": "style",
    "do_objectID": "99372EC2-49FB-40ED-931B-5CE7D33E94C2",
    "endMarkerType": 0,
    "miterLimit": 10,
    "startMarkerType": 0,
    "windingRule": 1
  }
}