{
  "_class": "shapePath",
  "booleanOperation": -1,
  "clippingMaskMode": 0,
  "do_objectID": "A986E0E2-A666-46F4-A107-5F1C63E0486A",
  "edited": true,
  "exportOptions": {
    "_class": "exportOptions",
    "do_objectID": "007A3EFC-726B-46CD-B809-2845BADE1F28",
    "exportFormats": [
    ],
    "includedLayerIds": [
    ],
    "layerOptions": 0,
    "shouldTrim": false
  },
  "frame": {
    "_class": "rect",
    "constrainProportions": false,
    "do_objectID": "88E6CF7F-1876-4465-972A-D0FF1A4CD0EF",
    "height": 3,
    "width": 3,
    "x": 18.6,
    "y": 15.6
  },
  "hasClippingMask": false,
  "isClosed": true,
  "isFixedToViewport": false,
  "isFlippedHorizontal": false,
  "isFlippedVertical": false,
  "isLocked": false,
  "isVisible": true,
  "layerListExpandedType": 0,
  "name": "Path",
  "nameIsFixed": false,
  "pointRadiusBehaviour": 1,
  "points": [
    {
      "_class": "curvePoint",
      "cornerRadius": 0,
      "curveFrom": "{0.23333333333333309, 1}",
      "curveMode": 4,
      "curveTo": "{0.76666666666666694, 0.96666666666666734}",
      "hasCurveFrom": true,
      "hasCurveTo": true,
      "point": "{0.5, 1}"
    },
    {
      "_class": "curvePoint",
      "cornerRadius": 0,
      "curveFrom": "{0, 0.23333333333333309}",
      "curveMode": 2,
      "curveTo": "{0, 0.76666666666666694}",
      "hasCurveFrom": true,
      "hasCurveTo": true,
      "point": "{0, 0.5}"
    },
    {
      "_class": "curvePoint",
      "cornerRadius": 0,
      "curveFrom": "{0.76666666666666694, 0}",
      "curveMode": 2,
      "curveTo": "{0.23333333333333309, 0}",
      "hasCurveFrom": true,
      "hasCurveTo": true,
      "point": "{0.5, 0}"
    },
    {
      "_class": "curvePoint",
      "cornerRadius": 0,
      "curveFrom": "{1, 0.73333333333333428}",
      "curveMode": 3,
      "curveTo": "{1, 0.23333333333333309}",
      "hasCurveFrom": true,
      "hasCurveTo": true,
      "point": "{1, 0.5}"
    }
  ],
  "resizingConstraint": 63,
  "resizingType": 0,
  "rotation": 0,
  "shouldBreakMaskChain": false,
  "style": {
    "_class": "style",
    "do_objectID": "61EF428D-33C0-40A8-B593-AA4F572BF4E1",
    "endMarkerType": 0,
    "miterLimit": 10,
    "startMarkerType": 0,
    "windingRule": 1
  }
}