{
  "_class": "group",
  "booleanOperation": -1,
  "clippingMaskMode": 0,
  "do_objectID": "F019EE1F-64A3-4395-962D-0FD0FAB2291D",
  "exportOptions": {
    "_class": "exportOptions",
    "do_objectID": "ABDD6D40-9AAA-4B1D-8DF2-3B04F96F3FD8",
    "exportFormats": [
    ],
    "includedLayerIds": [
    ],
    "layerOptions": 0,
    "shouldTrim": false
  },
  "frame": {
    "_class": "rect",
    "constrainProportions": false,
    "do_objectID": "7273C8AB-81E3-4E02-917E-C2F47352AB8B",
    "height": 49,
    "width": 49,
    "x": 307,
    "y": 490
  },
  "groupLayout": {
    "_class": "MSImmutableFreeformGroupLayout",
    "do_objectID": "7FE92A1C-FC4B-4D33-9BBC-3820DBA9A3AF"
  },
  "hasClickThrough": false,
  "hasClippingMask": false,
  "isFixedToViewport": false,
  "isFlippedHorizontal": false,
  "isFlippedVertical": false,
  "isLocked": false,
  "isVisible": true,
  "layerListExpandedType": 0,
  "layers": [
    {
      "class": "oval",
      "id": "ED667683-CF81-4FBF-B80A-966EC77DAC3D"
    },
    {
      "class": "symbolInstance",
      "id": "C2DC1603-AEA2-4B36-B6C5-66181C39B22B"
    }
  ],
  "name": "Group 5",
  "nameIsFixed": false,
  "resizingConstraint": 63,
  "resizingType": 0,
  "rotation": 0,
  "shouldBreakMaskChain": false,
  "style": {
    "_class": "style",
    "do_objectID": "45CB9EB1-4F5F-47F8-AC41-A3D7473F07B1",
    "endMarkerType": 0,
    "miterLimit": 10,
    "startMarkerType": 0,
    "windingRule": 1
  }
}