{
  "_class": "shapePath",
  "booleanOperation": 0,
  "clippingMaskMode": 0,
  "do_objectID": "D17D9F76-9F11-4FE1-A82A-96A59264D279",
  "edited": true,
  "exportOptions": {
    "_class": "exportOptions",
    "do_objectID": "426A3B1F-639B-458C-9961-C95B55F19D7F",
    "exportFormats": [
    ],
    "includedLayerIds": [
    ],
    "layerOptions": 0,
    "shouldTrim": false
  },
  "frame": {
    "_class": "rect",
    "constrainProportions": false,
    "do_objectID": "040A785E-ABB1-44ED-8534-64D9E1E433F1",
    "height": 12.00000000000001,
    "width": 13.99999999999999,
    "x": 1,
    "y": 2.000000000000014
  },
  "hasClippingMask": false,
  "isClosed": true,
  "isFixedToViewport": false,
  "isFlippedHorizontal": false,
  "isFlippedVertical": false,
  "isLocked": false,
  "isVisible": true,
  "layerListExpandedType": 0,
  "name": "BG",
  "nameIsFixed": true,
  "pointRadiusBehaviour": 1,
  "points": [
    {
      "_class": "curvePoint",
      "cornerRadius": 0,
      "curveFrom": "{0, 0.2499999999999982}",
      "curveMode": 1,
      "curveTo": "{0, 0.2499999999999982}",
      "hasCurveFrom": false,
      "hasCurveTo": false,
      "point": "{0, 0.2499999999999982}"
    },
    {
      "_class": "curvePoint",
      "cornerRadius": 0,
      "curveFrom": "{0.75000000000000067, 4.3021142204224806e-16}",
      "curveMode": 2,
      "curveTo": "{0.25000000000000072, -4.7470537982874621e-16}",
      "hasCurveFrom": true,
      "hasCurveTo": true,
      "point": "{0.50000000000000067, 0}"
    },
    {
      "_class": "curvePoint",
      "cornerRadius": 0,
      "curveFrom": "{1, 0.24999999999999992}",
      "curveMode": 1,
      "curveTo": "{1, 0.24999999999999992}",
      "hasCurveFrom": false,
      "hasCurveTo": false,
      "point": "{1, 0.24999999999999992}"
    },
    {
      "_class": "curvePoint",
      "cornerRadius": 0,
      "curveFrom": "{0.50000000000000011, 1}",
      "curveMode": 1,
      "curveTo": "{0.50000000000000011, 1}",
      "hasCurveFrom": false,
      "hasCurveTo": false,
      "point": "{0.50000000000000011, 1}"
    }
  ],
  "resizingConstraint": 63,
  "resizingType": 0,
  "rotation": 0,
  "shouldBreakMaskChain": false,
  "style": {
    "_class": "style",
    "do_objectID": "4DD5B307-1A2D-4E7B-9974-A3F73E81E0C3",
    "endMarkerType": 0,
    "fills": [
      {
        "_class": "fill",
        "color": {
          "_class": "color",
          "alpha": 0.2,
          "blue": 0,
          "green": 0,
          "red": 0
        },
        "fillType": 0,
        "isEnabled": true,
        "noiseIndex": 0,
        "noiseIntensity": 0,
        "patternFillType": 1,
        "patternTileScale": 1
      }
    ],
    "miterLimit": 10,
    "startMarkerType": 0,
    "windingRule": 1
  }
}