{
  "_class": "text",
  "attributedString": {
    "_class": "attributedString",
    "attributes": [
      {
        "_class": "stringAttribute",
        "attributes": {
          "MSAttributedStringColorAttribute": {
            "_class": "color",
            "alpha": 1,
            "blue": 0,
            "green": 0,
            "red": 0
          },
          "MSAttributedStringFontAttribute": {
            "_class": "fontDescriptor",
            "attributes": {
              "name": "Roboto-Bold",
              "size": 16
            }
          },
          "MSAttributedStringTextTransformAttribute": 0,
          "kerning": 0.2823529481887818,
          "paragraphStyle": {
            "_class": "paragraphStyle",
            "alignment": 1
          },
          "strikethroughStyle": 0,
          "underlineStyle": 0
        },
        "length": 7,
        "location": 0
      }
    ],
    "string": "00:00 h"
  },
  "automaticallyDrawOnUnderlyingPath": false,
  "booleanOperation": -1,
  "clippingMaskMode": 0,
  "do_objectID": "AF5FD318-88E5-42BA-BFBC-662E7AA48745",
  "dontSynchroniseWithSymbol": false,
  "exportOptions": {
    "_class": "exportOptions",
    "do_objectID": "D6C450F3-E5A8-4B4B-A900-A1E8FEAA6D3C",
    "exportFormats": [
    ],
    "includedLayerIds": [
    ],
    "layerOptions": 0,
    "shouldTrim": false
  },
  "frame": {
    "_class": "rect",
    "constrainProportions": false,
    "do_objectID": "4055B229-655C-437A-B937-1F8642EE8BDE",
    "height": 19,
    "width": 57,
    "x": 270,
    "y": 0
  },
  "glyphBounds": "{{0, 2}, {56, 14}}",
  "hasClippingMask": false,
  "isFixedToViewport": false,
  "isFlippedHorizontal": false,
  "isFlippedVertical": false,
  "isLocked": false,
  "isVisible": true,
  "layerListExpandedType": 0,
  "lineSpacingBehaviour": 2,
  "name": "00:00 h",
  "nameIsFixed": false,
  "resizingConstraint": 47,
  "resizingType": 0,
  "rotation": 0,
  "shouldBreakMaskChain": false,
  "style": {
    "_class": "style",
    "blur": {
      "_class": "blur",
      "center": "{0.5, 0.5}",
      "do_objectID": "BEBAF379-3F0B-4843-8756-A70256B22903",
      "isEnabled": false,
      "motionAngle": 0,
      "radius": 11.10000014305115,
      "saturation": 1,
      "type": 0
    },
    "do_objectID": "1A15DBEF-B10F-4920-A01B-2FD4B8AAC7EF",
    "endMarkerType": 0,
    "miterLimit": 10,
    "startMarkerType": 0,
    "textStyle": {
      "_class": "textStyle",
      "do_objectID": "BA559473-42E5-4BF0-8AA9-F8E2FE2929CC",
      "encodedAttributes": {
        "MSAttributedStringColorAttribute": {
          "_class": "color",
          "alpha": 1,
          "blue": 0,
          "green": 0,
          "red": 0
        },
        "MSAttributedStringFontAttribute": {
          "_class": "fontDescriptor",
          "attributes": {
            "name": "Roboto-Bold",
            "size": 16
          }
        },
        "MSAttributedStringTextTransformAttribute": 0,
        "kerning": 0.2823529481887818,
        "paragraphStyle": {
          "_class": "paragraphStyle",
          "alignment": 1
        },
        "strikethroughStyle": 0,
        "underlineStyle": 0
      },
      "verticalAlignment": 0
    },
    "windingRule": 1
  },
  "textBehaviour": 0,
  "userInfo": {
    "com.animaapp.stc-sketch-plugin": {
      "kModelPropertiesKey": {
        "isAutoWidth": 1
      }
    }
  }
}