{
  "_class": "symbolInstance",
  "booleanOperation": -1,
  "clippingMaskMode": 0,
  "do_objectID": "2A119F2C-8F2F-48E4-9154-16C45205F0CD",
  "exportOptions": {
    "_class": "exportOptions",
    "do_objectID": "64533F4F-5221-4577-805E-F56C28908E60",
    "exportFormats": [
    ],
    "includedLayerIds": [
    ],
    "layerOptions": 0,
    "shouldTrim": false
  },
  "frame": {
    "_class": "rect",
    "constrainProportions": false,
    "do_objectID": "50072171-74DA-432C-80E4-941146C57841",
    "height": 24,
    "width": 24,
    "x": 13,
    "y": 12.587841608693
  },
  "hasClippingMask": false,
  "horizontalSpacing": 0,
  "isFixedToViewport": false,
  "isFlippedHorizontal": false,
  "isFlippedVertical": false,
  "isLocked": false,
  "isVisible": true,
  "layerListExpandedType": 0,
  "name": "navigation",
  "nameIsFixed": false,
  "overrideValues": [
  ],
  "resizingConstraint": 63,
  "resizingType": 0,
  "rotation": 0,
  "scale": 1,
  "shouldBreakMaskChain": false,
  "style": {
    "_class": "style",
    "do_objectID": "24315A43-299D-4DB6-8E1B-0E7903508703",
    "endMarkerType": 0,
    "miterLimit": 10,
    "startMarkerType": 0,
    "windingRule": 1
  },
  "symbolID": "BCBEB804-A684-46C8-901A-25A7FD00F205",
  "verticalSpacing": 0
}