{
  "_class": "group",
  "booleanOperation": -1,
  "clippingMaskMode": 0,
  "do_objectID": "29031310-3F8F-4F39-9DA5-C46816B19037",
  "exportOptions": {
    "_class": "exportOptions",
    "do_objectID": "9B8194B7-049A-40BB-AB30-DD4CA6FCB4B2",
    "exportFormats": [
    ],
    "includedLayerIds": [
    ],
    "layerOptions": 0,
    "shouldTrim": false
  },
  "frame": {
    "_class": "rect",
    "constrainProportions": false,
    "do_objectID": "697A92EE-8882-4E83-A894-3BE1DFF7BCE1",
    "height": 49,
    "width": 49,
    "x": 307,
    "y": 267
  },
  "groupLayout": {
    "_class": "MSImmutableFreeformGroupLayout",
    "do_objectID": "D19733AE-3D50-4BE0-A631-07D80759554B"
  },
  "hasClickThrough": false,
  "hasClippingMask": false,
  "isFixedToViewport": false,
  "isFlippedHorizontal": false,
  "isFlippedVertical": false,
  "isLocked": false,
  "isVisible": true,
  "layerListExpandedType": 0,
  "layers": [
    {
      "class": "oval",
      "id": "13C11E88-2BED-4FC2-AE9B-DCD877E929B1"
    },
    {
      "class": "symbolInstance",
      "id": "43D924DD-AB54-49C7-867A-5BDB116F69CD"
    }
  ],
  "name": "Group 5",
  "nameIsFixed": false,
  "resizingConstraint": 63,
  "resizingType": 0,
  "rotation": 0,
  "shouldBreakMaskChain": false,
  "style": {
    "_class": "style",
    "do_objectID": "64B9DA01-EB3A-4921-B6AE-69328D3F5CEA",
    "endMarkerType": 0,
    "miterLimit": 10,
    "startMarkerType": 0,
    "windingRule": 1
  }
}